{
    "weapon":[
        {
            "id": "0",
            "name": "Uchigatana",
            "image": "assets/items/weapon/uchigatana.png",
            "description": "A unique katana characterized by the fine craftsmanship of an eastern land where it was forged.\nThe finely-sharpened blade cuts flesh like butter and causes bleeding, but breaks easily as a result.",
            "skill": "Hold",
            "attack": 115
        },
        {
            "id": "1",
            "name": "Greatsword",
            "image": "assets/items/weapon/greatsword.png",
            "description": "This ultra greatsword, with its thick blade, is one of the heaviest of its kind.\nHighly destructive if intolerably heavy.\nThere would appear to be some credence to the rumors that this sword tested the true limits of human strength.",
            "skill": "Stomp",
            "attack": 159
        },
        {
            "id": "2",
            "name": "Bandit's Knife",
            "image": "assets/items/weapon/bandits_knife.png",
            "description": "A wide single-edged shortsword.\nPrimarily a slicing weapon, but its blade is crafted to cause bleeding, making it a favorite of lowly thieves and bandits.",
            "skill": "Quickstep",
            "attack": 79
        },
        {
            "id": "3",
            "name": "Wolf Knight's Greatsword",
            "image": "assets/items/weapon/wolf_knights_greatsword.png",
            "description": "Greatsword of a knight tainted by the dark of the Abyss, and master of the wolf's blood of Farron.\nThe wolf knight was the first Abyss Watcher, and his sword is more punishing against creations of the abyss.",
            "skill": "Wolf Sword",
            "attack": 139
        },
        {
            "id": "4",
            "name": "Moonlight Greatsword",
            "image": "assets/items/weapon/moonlight_greatsword.png",
            "description": "Legendary dragon weapon associated with Seath the paledrake.\nCharge strong attack to its limit to unleash moonlight wave.\nOceiros, the Consumed King, was infatuated with the search for moonlight, but in the end, it never revealed itself to him.",
            "skill": "Moonlight Vortex",
            "attack": 69
        }
    ]
}